{
  "formatVersion": 1,
  "database": {
    "version": 2,
    "identityHash": "3b59f888ab0b35c62c8c304a6414304a",
    "entities": [
      {
        "tableName": "LightSensorReading",
        "createSql": "CREATE TABLE IF NOT EXISTS `${TABLE_NAME}` (`uuid_light` INTEGER PRIMARY KEY AUTOINCREMENT NOT NULL, `timestamp_light` INTEGER NOT NULL, `reading_light` REAL, `latitude` TEXT, `longitude` TEXT, `address` TEXT)",
        "fields": [
          {
            "fieldPath": "uuid",
            "columnName": "uuid_light",
            "affinity": "INTEGER",
            "notNull": true
          },
          {
            "fieldPath": "timestamp",
            "columnName": "timestamp_light",
            "affinity": "INTEGER",
            "notNull": true
          },
          {
            "fieldPath": "sensorReading",
            "columnName": "reading_light",
            "affinity": "REAL",
            "notNull": false
          },
          {
            "fieldPath": "location.latitude",
            "columnName": "latitude",
            "affinity": "TEXT",
            "notNull": false
          },
          {
            "fieldPath": "location.longitude",
            "columnName": "longitude",
            "affinity": "TEXT",
            "notNull": false
          },
          {
            "fieldPath": "location.address",
            "columnName": "address",
            "affinity": "TEXT",
            "notNull": false
          }
        ],
        "primaryKey": {
          "columnNames": [
            "uuid_light"
          ],
          "autoGenerate": true
        },
        "indices": [],
        "foreignKeys": []
      },
      {
        "tableName": "TemperatureSensorReading",
        "createSql": "CREATE TABLE IF NOT EXISTS `${TABLE_NAME}` (`uuid_temperature` INTEGER PRIMARY KEY AUTOINCREMENT NOT NULL, `timestamp_temperature` INTEGER NOT NULL, `reading_temperature` REAL, `latitude` TEXT, `longitude` TEXT, `address` TEXT)",
        "fields": [
          {
            "fieldPath": "uuid",
            "columnName": "uuid_temperature",
            "affinity": "INTEGER",
            "notNull": true
          },
          {
            "fieldPath": "timestamp",
            "columnName": "timestamp_temperature",
            "affinity": "INTEGER",
            "notNull": true
          },
          {
            "fieldPath": "sensorReading",
            "columnName": "reading_temperature",
            "affinity": "REAL",
            "notNull": false
          },
          {
            "fieldPath": "location.latitude",
            "columnName": "latitude",
            "affinity": "TEXT",
            "notNull": false
          },
          {
            "fieldPath": "location.longitude",
            "columnName": "longitude",
            "affinity": "TEXT",
            "notNull": false
          },
          {
            "fieldPath": "location.address",
            "columnName": "address",
            "affinity": "TEXT",
            "notNull": false
          }
        ],
        "primaryKey": {
          "columnNames": [
            "uuid_temperature"
          ],
          "autoGenerate": true
        },
        "indices": [],
        "foreignKeys": []
      },
      {
        "tableName": "DewPointAndAbsHumidityReading",
        "createSql": "CREATE TABLE IF NOT EXISTS `${TABLE_NAME}` (`uuid_DewPointAbsHumidity` INTEGER PRIMARY KEY AUTOINCREMENT NOT NULL, `timestamp_DewPointAbsHumidity` INTEGER NOT NULL, `temperature` REAL, `relativeHumidity` REAL, `dewPoint` REAL, `absHumidityReading` REAL, `latitude` TEXT, `longitude` TEXT, `address` TEXT)",
        "fields": [
          {
            "fieldPath": "uuid",
            "columnName": "uuid_DewPointAbsHumidity",
            "affinity": "INTEGER",
            "notNull": true
          },
          {
            "fieldPath": "timestamp",
            "columnName": "timestamp_DewPointAbsHumidity",
            "affinity": "INTEGER",
            "notNull": true
          },
          {
            "fieldPath": "temperature",
            "columnName": "temperature",
            "affinity": "REAL",
            "notNull": false
          },
          {
            "fieldPath": "relativeHumidity",
            "columnName": "relativeHumidity",
            "affinity": "REAL",
            "notNull": false
          },
          {
            "fieldPath": "dewPoint",
            "columnName": "dewPoint",
            "affinity": "REAL",
            "notNull": false
          },
          {
            "fieldPath": "absHumidityReading",
            "columnName": "absHumidityReading",
            "affinity": "REAL",
            "notNull": false
          },
          {
            "fieldPath": "location.latitude",
            "columnName": "latitude",
            "affinity": "TEXT",
            "notNull": false
          },
          {
            "fieldPath": "location.longitude",
            "columnName": "longitude",
            "affinity": "TEXT",
            "notNull": false
          },
          {
            "fieldPath": "location.address",
            "columnName": "address",
            "affinity": "TEXT",
            "notNull": false
          }
        ],
        "primaryKey": {
          "columnNames": [
            "uuid_DewPointAbsHumidity"
          ],
          "autoGenerate": true
        },
        "indices": [],
        "foreignKeys": []
      },
      {
        "tableName": "HumiditySensorReading",
        "createSql": "CREATE TABLE IF NOT EXISTS `${TABLE_NAME}` (`uuid_humidity` INTEGER PRIMARY KEY AUTOINCREMENT NOT NULL, `timestamp_humidity` INTEGER NOT NULL, `reading_humidity` REAL, `latitude` TEXT, `longitude` TEXT, `address` TEXT)",
        "fields": [
          {
            "fieldPath": "uuid",
            "columnName": "uuid_humidity",
            "affinity": "INTEGER",
            "notNull": true
          },
          {
            "fieldPath": "timestamp",
            "columnName": "timestamp_humidity",
            "affinity": "INTEGER",
            "notNull": true
          },
          {
            "fieldPath": "sensorReading",
            "columnName": "reading_humidity",
            "affinity": "REAL",
            "notNull": false
          },
          {
            "fieldPath": "location.latitude",
            "columnName": "latitude",
            "affinity": "TEXT",
            "notNull": false
          },
          {
            "fieldPath": "location.longitude",
            "columnName": "longitude",
            "affinity": "TEXT",
            "notNull": false
          },
          {
            "fieldPath": "location.address",
            "columnName": "address",
            "affinity": "TEXT",
            "notNull": false
          }
        ],
        "primaryKey": {
          "columnNames": [
            "uuid_humidity"
          ],
          "autoGenerate": true
        },
        "indices": [],
        "foreignKeys": []
      },
      {
        "tableName": "PressureSensorReading",
        "createSql": "CREATE TABLE IF NOT EXISTS `${TABLE_NAME}` (`uuid_pressure` INTEGER PRIMARY KEY AUTOINCREMENT NOT NULL, `timestamp_pressure` INTEGER NOT NULL, `reading_pressure` REAL, `latitude` TEXT, `longitude` TEXT, `address` TEXT)",
        "fields": [
          {
            "fieldPath": "uuid",
            "columnName": "uuid_pressure",
            "affinity": "INTEGER",
            "notNull": true
          },
          {
            "fieldPath": "timestamp",
            "columnName": "timestamp_pressure",
            "affinity": "INTEGER",
            "notNull": true
          },
          {
            "fieldPath": "sensorReading",
            "columnName": "reading_pressure",
            "affinity": "REAL",
            "notNull": false
          },
          {
            "fieldPath": "location.latitude",
            "columnName": "latitude",
            "affinity": "TEXT",
            "notNull": false
          },
          {
            "fieldPath": "location.longitude",
            "columnName": "longitude",
            "affinity": "TEXT",
            "notNull": false
          },
          {
            "fieldPath": "location.address",
            "columnName": "address",
            "affinity": "TEXT",
            "notNull": false
          }
        ],
        "primaryKey": {
          "columnNames": [
            "uuid_pressure"
          ],
          "autoGenerate": true
        },
        "indices": [],
        "foreignKeys": []
      },
      {
        "tableName": "OneCallWeather",
        "createSql": "CREATE TABLE IF NOT EXISTS `${TABLE_NAME}` (`uuid` INTEGER PRIMARY KEY AUTOINCREMENT NOT NULL, `lat` REAL NOT NULL, `lon` REAL NOT NULL, `timezone` TEXT NOT NULL, `timezone_offset` INTEGER NOT NULL, `dt` REAL NOT NULL, `sunrise` REAL NOT NULL, `sunset` REAL NOT NULL, `temp` REAL NOT NULL, `feels_like` REAL NOT NULL, `pressure` REAL NOT NULL, `humidity` REAL NOT NULL, `dew_point` REAL NOT NULL, `uvi` REAL NOT NULL, `clouds` REAL NOT NULL, `visibility` REAL NOT NULL, `wind_speed` REAL NOT NULL, `wind_deg` REAL NOT NULL)",
        "fields": [
          {
            "fieldPath": "uuid",
            "columnName": "uuid",
            "affinity": "INTEGER",
            "notNull": true
          },
          {
            "fieldPath": "lat",
            "columnName": "lat",
            "affinity": "REAL",
            "notNull": true
          },
          {
            "fieldPath": "lon",
            "columnName": "lon",
            "affinity": "REAL",
            "notNull": true
          },
          {
            "fieldPath": "timezone",
            "columnName": "timezone",
            "affinity": "TEXT",
            "notNull": true
          },
          {
            "fieldPath": "timezone_offset",
            "columnName": "timezone_offset",
            "affinity": "INTEGER",
            "notNull": true
          },
          {
            "fieldPath": "current.dt",
            "columnName": "dt",
            "affinity": "REAL",
            "notNull": true
          },
          {
            "fieldPath": "current.sunrise",
            "columnName": "sunrise",
            "affinity": "REAL",
            "notNull": true
          },
          {
            "fieldPath": "current.sunset",
            "columnName": "sunset",
            "affinity": "REAL",
            "notNull": true
          },
          {
            "fieldPath": "current.temp",
            "columnName": "temp",
            "affinity": "REAL",
            "notNull": true
          },
          {
            "fieldPath": "current.feels_like",
            "columnName": "feels_like",
            "affinity": "REAL",
            "notNull": true
          },
          {
            "fieldPath": "current.pressure",
            "columnName": "pressure",
            "affinity": "REAL",
            "notNull": true
          },
          {
            "fieldPath": "current.humidity",
            "columnName": "humidity",
            "affinity": "REAL",
            "notNull": true
          },
          {
            "fieldPath": "current.dew_point",
            "columnName": "dew_point",
            "affinity": "REAL",
            "notNull": true
          },
          {
            "fieldPath": "current.uvi",
            "columnName": "uvi",
            "affinity": "REAL",
            "notNull": true
          },
          {
            "fieldPath": "current.clouds",
            "columnName": "clouds",
            "affinity": "REAL",
            "notNull": true
          },
          {
            "fieldPath": "current.visibility",
            "columnName": "visibility",
            "affinity": "REAL",
            "notNull": true
          },
          {
            "fieldPath": "current.wind_speed",
            "columnName": "wind_speed",
            "affinity": "REAL",
            "notNull": true
          },
          {
            "fieldPath": "current.wind_deg",
            "columnName": "wind_deg",
            "affinity": "REAL",
            "notNull": true
          }
        ],
        "primaryKey": {
          "columnNames": [
            "uuid"
          ],
          "autoGenerate": true
        },
        "indices": [],
        "foreignKeys": []
      }
    ],
    "views": [],
    "setupQueries": [
      "CREATE TABLE IF NOT EXISTS room_master_table (id INTEGER PRIMARY KEY,identity_hash TEXT)",
      "INSERT OR REPLACE INTO room_master_table (id,identity_hash) VALUES(42, '3b59f888ab0b35c62c8c304a6414304a')"
    ]
  }
}